crypto_prices/__init__.py
crypto_prices/price_fetcher.py
crypto_prices-0.0.1.dist-info/LICENSE
crypto_prices-0.0.1.dist-info/METADATA
crypto_prices-0.0.1.dist-info/WHEEL
crypto_prices-0.0.1.dist-info/top_level.txt
crypto_prices-0.0.1.dist-info/RECORD
